letigre_moto-0.0.1.dist-info/DESCRIPTION.rst
letigre_moto-0.0.1.dist-info/METADATA
letigre_moto-0.0.1.dist-info/RECORD
letigre_moto-0.0.1.dist-info/WHEEL
letigre_moto-0.0.1.dist-info/entry_points.txt
letigre_moto-0.0.1.dist-info/metadata.json
letigre_moto-0.0.1.dist-info/top_level.txt
moto/__init__.py
moto/backends.py
moto/compat.py
moto/server.py
moto/settings.py
moto/acm/__init__.py
moto/acm/models.py
moto/acm/responses.py
moto/acm/urls.py
moto/acm/utils.py
moto/apigateway/__init__.py
moto/apigateway/exceptions.py
moto/apigateway/models.py
moto/apigateway/responses.py
moto/apigateway/urls.py
moto/apigateway/utils.py
moto/autoscaling/__init__.py
moto/autoscaling/exceptions.py
moto/autoscaling/models.py
moto/autoscaling/responses.py
moto/autoscaling/urls.py
moto/awslambda/__init__.py
moto/awslambda/models.py
moto/awslambda/responses.py
moto/awslambda/urls.py
moto/awslambda/utils.py
moto/batch/__init__.py
moto/batch/exceptions.py
moto/batch/models.py
moto/batch/responses.py
moto/batch/urls.py
moto/batch/utils.py
moto/cloudformation/__init__.py
moto/cloudformation/exceptions.py
moto/cloudformation/models.py
moto/cloudformation/parsing.py
moto/cloudformation/responses.py
moto/cloudformation/urls.py
moto/cloudformation/utils.py
moto/cloudwatch/__init__.py
moto/cloudwatch/models.py
moto/cloudwatch/responses.py
moto/cloudwatch/urls.py
moto/cloudwatch/utils.py
moto/cognitoidentity/__init__.py
moto/cognitoidentity/models.py
moto/cognitoidentity/responses.py
moto/cognitoidentity/urls.py
moto/cognitoidentity/utils.py
moto/cognitoidp/__init__.py
moto/cognitoidp/exceptions.py
moto/cognitoidp/models.py
moto/cognitoidp/responses.py
moto/cognitoidp/urls.py
moto/cognitoidp/resources/jwks-private.json
moto/cognitoidp/resources/jwks-public.json
moto/config/__init__.py
moto/config/exceptions.py
moto/config/models.py
moto/config/responses.py
moto/config/urls.py
moto/core/__init__.py
moto/core/exceptions.py
moto/core/models.py
moto/core/responses.py
moto/core/urls.py
moto/core/utils.py
moto/datapipeline/__init__.py
moto/datapipeline/models.py
moto/datapipeline/responses.py
moto/datapipeline/urls.py
moto/datapipeline/utils.py
moto/dynamodb/__init__.py
moto/dynamodb/comparisons.py
